cheqlist/__init__.py
cheqlist/__main__.py
cheqlist/app.py
cheqlist/appdirs.py
cheqlist/pastewindow.py
cheqlist/undocommands.py
cheqlist/undowidget.py
cheqlist/utils.py
cheqlist/data/cheqlist.ini.skel
cheqlist-0.3.2.data/data/share/applications/cheqlist.desktop
cheqlist-0.3.2.data/data/share/mime/packages/cheqlist.xml
cheqlist-0.3.2.dist-info/AUTHORS
cheqlist-0.3.2.dist-info/LICENSE
cheqlist-0.3.2.dist-info/METADATA
cheqlist-0.3.2.dist-info/WHEEL
cheqlist-0.3.2.dist-info/entry_points.txt
cheqlist-0.3.2.dist-info/top_level.txt
cheqlist-0.3.2.dist-info/RECORD
