Metadata-Version: 2.1
Name: cheqlist
Version: 0.3.2
Summary: A simple Qt checklist.
Home-page: https://github.com/Kwpolska/cheqlist
Author: Chris Warrick
Author-email: chris@chriswarrick.com
License: 3-clause BSD
Keywords: cheqlist
Platform: any
Classifier: Development Status :: 3 - Alpha
Classifier: Environment :: X11 Applications :: Qt
Classifier: License :: OSI Approved :: BSD License
Classifier: Topic :: Office/Business :: Scheduling
Classifier: Programming Language :: Python :: 3
Classifier: Programming Language :: Python :: 3.3
Classifier: Programming Language :: Python :: 3.4
Classifier: Programming Language :: Python :: 3.5
Classifier: Programming Language :: Python :: 3.6
Classifier: Programming Language :: Python :: 3.7
Classifier: Programming Language :: Python :: 3.8
Requires-Dist: PySide2
